{"Title":"Another Earth","Year":"2011","Rated":"PG-13","Released":"12 Oct 2011","Runtime":"92 min","Genre":"Drama, Romance, Sci-Fi","Director":"Mike Cahill","Writer":"Mike Cahill, Brit Marling","Actors":"William Mapother, Brit Marling, Matthew-Lee Erlbach, DJ Flava","Plot":"On the night of the discovery of a duplicate Earth in the Solar system, an ambitious young student and an accomplished composer cross paths in a tragic accident.","Language":"English","Country":"USA","Awards":"7 wins & 12 nominations.","Poster":"MV5BMTAzNTIzMjkxNjJeQTJeQWpwZ15BbWU3MDEwNDQ2OTU@._V1_SX300.jpg","Metascore":"66","imdbRating":"7.0","imdbVotes":"49,618","imdbID":"tt1549572","Type":"movie","Response":"True","size":"6035360"}
