{"Title":"Juno","Year":"2007","Rated":"PG-13","Released":"25 Dec 2007","Runtime":"96 min","Genre":"Comedy, Drama, Romance","Director":"Jason Reitman","Writer":"Diablo Cody","Actors":"Ellen Page, Michael Cera, Jennifer Garner, Jason Bateman","Plot":"Faced with an unplanned pregnancy, an offbeat young woman makes an unusual decision regarding her unborn child.","Language":"English","Country":"USA","Awards":"Won 1 Oscar. Another 88 wins & 57 nominations.","Poster":"http://ia.media-imdb.com/images/M/MV5BMTgxMjgyMTcyNF5BMl5BanBnXkFtZTcwMDg1MTU1MQ@@._V1_SX300.jpg","Metascore":"81","imdbRating":"7.6","imdbVotes":"334,753","imdbID":"tt0467406","Type":"movie","Response":"True"}