{"Title":"Inspector Morse","Year":"1987–2000","Rated":"N/A","Released":"04 Feb 1988","Runtime":"100 min","Genre":"Crime, Drama, Mystery","Director":"N/A","Writer":"N/A","Actors":"John Thaw, Kevin Whately, James Grout","Plot":"Inspector Morse has an ear for music, a taste for beer and a nose for crime. He sets out with Sergeant Lewis to solve each intriguing case.","Language":"English","Country":"UK, USA","Awards":"9 wins & 12 nominations.","Poster":"http://ia.media-imdb.com/images/M/MV5BMTI5NTMxOTU3Nl5BMl5BanBnXkFtZTcwNjU3NTAwMQ@@._V1_SX300.jpg","Metascore":"N/A","imdbRating":"8.1","imdbVotes":"4,449","imdbID":"tt0092379","Type":"series","Response":"True"}