{"Title":"Little Miss Sunshine","Year":"2006","Rated":"R","Released":"18 Aug 2006","Runtime":"101 min","Genre":"Adventure, Comedy, Drama","Director":"Jonathan Dayton, Valerie Faris","Writer":"Michael Arndt","Actors":"Abigail Breslin, Greg Kinnear, Paul Dano, Alan Arkin","Plot":"A family determined to get their young daughter into the finals of a beauty pageant take a cross-country trip in their VW bus.","Language":"English","Country":"USA","Awards":"Won 2 Oscars. Another 65 wins & 67 nominations.","Poster":"MV5BMTgzNTgzODU0NV5BMl5BanBnXkFtZTcwMjEyMjMzMQ@@._V1_SX300.jpg","Metascore":"80","imdbRating":"7.9","imdbVotes":"286,784","imdbID":"tt0449059","Type":"movie","Response":"True"}
